hydra_auto_schema/__init__.py
hydra_auto_schema/__main__.py
hydra_auto_schema/auto_schema.py
hydra_auto_schema/auto_schema_test.py
hydra_auto_schema/customize.py
hydra_auto_schema/filewatcher.py
hydra_auto_schema/hydra_schema.py
hydra_auto_schema/py.typed
hydra_auto_schema/utils.py
hydra_plugins/auto_schema/__init__.py
hydra_plugins/auto_schema/auto_schema_plugin.py
hydra_auto_schema-0.0.6.dist-info/METADATA
hydra_auto_schema-0.0.6.dist-info/WHEEL
hydra_auto_schema-0.0.6.dist-info/entry_points.txt
hydra_auto_schema-0.0.6.dist-info/licenses/LICENSE
hydra_auto_schema-0.0.6.dist-info/RECORD
