Metadata-Version: 2.3
Name: hydra-auto-schema
Version: 0.0.6
Summary: Automagically generate yaml schemas for your Hydra config files
Author-email: Fabrice Normandin <normandf@mila.quebec>
License-File: LICENSE
Requires-Python: >=3.10
Requires-Dist: docstring-parser>=0.16
Requires-Dist: hydra-core>=1.3.2
Requires-Dist: hydra-zen>=0.13.0
Requires-Dist: omegaconf>=2.3.0
Requires-Dist: pydantic>=2.9.2
Requires-Dist: rich>=13.9.3
Requires-Dist: tqdm>=4.66.6
Requires-Dist: watchdog>=5.0.3
